{
  "task": "搜索~/Downloads目录的png文件并设置为壁纸",
  "task_hash": "7fe807d5",
  "keywords": [
    "壁纸",
    "设置",
    "搜索~/Downloads目录的png文件并设置为壁纸",
    "目录",
    "文件",
    "搜索"
  ],
  "reasoning_chain": {
    "thought_chain": {
      "task_understanding": "用户希望从下载目录找到PNG图片并设置为桌面壁纸",
      "task_decomposition": "1. 搜索~/Downloads目录下的png文件；2. 选择合适的图片；3. 调用系统设置更换壁纸；4. 验证壁纸是否生效",
      "agent_selection": [
        {
          "step": 1,
          "agent": "FileAgent",
          "reason": "需要文件搜索功能"
        },
        {
          "step": 2,
          "agent": "FileAgent",
          "reason": "需要文件选择功能"
        },
        {
          "step": 3,
          "agent": "SettingsAgent",
          "reason": "需要系统设置功能"
        },
        {
          "step": 4,
          "agent": "SettingsAgent",
          "reason": "需要验证系统状态"
        }
      ],
      "risk_assessment": "~/Downloads目录可能没有png文件",
      "fallback_plan": "如果没有png文件，提示用户上传图片或搜索其他格式"
    },
    "execution_plan": [
      {
        "step": 1,
        "action": "在~/Downloads目录搜索*.png文件",
        "agent": "FileAgent"
      },
      {
        "step": 2,
        "action": "获取搜索结果的第一个png文件路径",
        "agent": "FileAgent"
      },
      {
        "step": 3,
        "action": "打开系统设置-外观-壁纸，设置选中的图片",
        "agent": "SettingsAgent"
      },
      {
        "step": 4,
        "action": "检查桌面壁纸是否已更新",
        "agent": "SettingsAgent"
      }
    ],
    "milestone_markers": [
      "search_complete",
      "file_selected",
      "wallpaper_set",
      "verification_done"
    ],
    "_raw_output": "```json\n{\n    \"thought_chain\": {\n        \"task_understanding\": \"用户希望从下载目录找到PNG图片并设置为桌面壁纸\",\n        \"task_decomposition\": \"1. 搜索~/Downloads目录下的png文件；2. 选择合适的图片；3. 调用系统设置更换壁纸；4. 验证壁纸是否生效\",\n        \"agent_selection\": [\n            {\"step\": 1, \"agent\": \"FileAgent\", \"reason\": \"需要文件搜索功能\"},\n            {\"step\": 2, \"agent\": \"FileAgent\", \"reason\": \"需要文件选择功能\"},\n            {\"step\": 3, \"agent\": \"SettingsAgent\", \"reason\": \"需要系统设置功能\"},\n            {\"step\": 4, \"agent\": \"SettingsAgent\", \"reason\": \"需要验证系统状态\"}\n        ],\n        \"risk_assessment\": \"~/Downloads目录可能没有png文件\",\n        \"fallback_plan\": \"如果没有png文件，提示用户上传图片或搜索其他格式\"\n    },\n    \"execution_plan\": [\n        {\"step\": 1, \"action\": \"在~/Downloads目录搜索*.png文件\", \"agent\": \"FileAgent\"},\n        {\"step\": 2, \"action\": \"获取搜索结果的第一个png文件路径\", \"agent\": \"FileAgent\"},\n        {\"step\": 3, \"action\": \"打开系统设置-外观-壁纸，设置选中的图片\", \"agent\": \"SettingsAgent\"},\n        {\"step\": 4, \"action\": \"检查桌面壁纸是否已更新\", \"agent\": \"SettingsAgent\"}\n    ],\n    \"milestone_markers\": [\"search_complete\", \"file_selected\", \"wallpaper_set\", \"verification_done\"]\n}\n```",
    "_retry_count": 1
  },
  "execution_result": "测试执行：成功搜索到png文件",
  "gui_action": {
    "thought_chain": {
      "current_state": "我正在文件管理器中，需要找到~/Downloads目录下的PNG文件。当前界面显示的是个人目录，我需要先导航到Downloads文件夹。我看到左侧导航栏中有Downloads选项，但需要先点击个人目录下的Downloads文件夹来访问该目录。我应该点击左侧导航栏中的Downloads文件夹，这样就可以进入Downloads目录，然后才能搜索PNG文件。",
      "task_analysis": "我需要先导航到Downloads目录，然后搜索PNG文件。当前界面显示的是个人目录，我需要点击左侧导航栏中的Downloads文件夹来访问该目录。这是完成任务的第一步。",
      "next_step": "click",
      "reasoning": "我需要先导航到Downloads目录，然后才能搜索PNG文件。当前界面显示的是个人目录，我应该点击左侧导航栏中的Downloads文件夹，这样就可以进入Downloads目录，然后才能搜索PNG文件。"
    },
    "action": {
      "type": "click",
      "params": {
        "坐标": "(194,481)"
      }
    },
    "confidence": 0.95,
    "milestone": "进入Downloads目录",
    "_raw_output": "```json\n{\n    \"thought_chain\": {\n        \"current_state\": \"我正在文件管理器中，需要找到~/Downloads目录下的PNG文件。当前界面显示的是个人目录，我需要先导航到Downloads文件夹。我看到左侧导航栏中有Downloads选项，但需要先点击个人目录下的Downloads文件夹来访问该目录。我应该点击左侧导航栏中的Downloads文件夹，这样就可以进入Downloads目录，然后才能搜索PNG文件。\",\n        \"task_analysis\": \"我需要先导航到Downloads目录，然后搜索PNG文件。当前界面显示的是个人目录，我需要点击左侧导航栏中的Downloads文件夹来访问该目录。这是完成任务的第一步。\",\n        \"next_step\": \"click\",\n        \"reasoning\": \"我需要先导航到Downloads目录，然后才能搜索PNG文件。当前界面显示的是个人目录，我应该点击左侧导航栏中的Downloads文件夹，这样就可以进入Downloads目录，然后才能搜索PNG文件。\"\n    },\n    \"action\": {\n        \"type\": \"click\",\n        \"params\": {\n            \"坐标\": \"(194,481)\"\n        }\n    },\n    \"confidence\": 0.95,\n    \"milestone\": \"进入Downloads目录\"\n}\n```"
  },
  "agents_involved": [
    "FileAgent",
    "SettingsAgent"
  ],
  "success": true,
  "screenshot_paths": [
    "/data1/cyx/anything/麒麟OS桌面.png"
  ],
  "screenshot_count": 1,
  "timestamp": "2025-12-05 13:24:42",
  "timestamp_unix": 1764912282,
  "metadata": {
    "source": "system2_memory",
    "reused": false,
    "mcp_validated": true
  }
}